testipynb/__init__.py
testipynb/testipynb.py
testipynb-0.0.1.dist-info/DESCRIPTION.rst
testipynb-0.0.1.dist-info/METADATA
testipynb-0.0.1.dist-info/RECORD
testipynb-0.0.1.dist-info/WHEEL
testipynb-0.0.1.dist-info/metadata.json
testipynb-0.0.1.dist-info/top_level.txt
