Metadata-Version: 2.0
Name: testipynb
Version: 0.0.1
Summary: testipynb
Home-page: http://github.com/lheagy/testipynb
Author: Lindsey Heagy
Author-email: lindseyheagy@gmail.com
License: MIT License
Download-URL: http://github.com/lheagy/testipynb
Keywords: jupyter,testing
Platform: Windows
Platform: Linux
Platform: Solaris
Platform: Mac OS-X
Platform: Unix
Classifier: Development Status :: 4 - Beta
Classifier: Intended Audience :: Education
Classifier: Intended Audience :: Science/Research
Classifier: License :: OSI Approved :: MIT License
Classifier: Programming Language :: Python
Classifier: Topic :: Scientific/Engineering
Classifier: Topic :: Scientific/Engineering :: Mathematics
Classifier: Topic :: Scientific/Engineering :: Physics
Classifier: Operating System :: Microsoft :: Windows
Classifier: Operating System :: POSIX
Classifier: Operating System :: Unix
Classifier: Operating System :: MacOS
Classifier: Natural Language :: English
Requires-Dist: future
Requires-Dist: numpy (>=1.7)
Requires-Dist: ipywidgets
Requires-Dist: jupyter
Requires-Dist: nbconvert
Requires-Dist: nbformat
Requires-Dist: properties
